import_nbmodule/__init__.py
import_nbmodule/import_nbmodule.py
import_nbmodule-0.0.2.dist-info/LICENSE
import_nbmodule-0.0.2.dist-info/METADATA
import_nbmodule-0.0.2.dist-info/WHEEL
import_nbmodule-0.0.2.dist-info/top_level.txt
import_nbmodule-0.0.2.dist-info/RECORD
